README.md
setup.cfg
setup.py
distributions_GMG/Binomialdistribution.py
distributions_GMG/Gaussiandistribution.py
distributions_GMG/Generaldistribution.py
distributions_GMG/__init__.py
distributions_GMG.egg-info/PKG-INFO
distributions_GMG.egg-info/SOURCES.txt
distributions_GMG.egg-info/dependency_links.txt
distributions_GMG.egg-info/not-zip-safe
distributions_GMG.egg-info/top_level.txt