Metadata-Version: 1.0
Name: distributions-GMG
Version: 0.1
Summary: Gaussian distributions
Home-page: UNKNOWN
Author: Gonzalo Munilla Garrido
Author-email: UNKNOWN
License: UNKNOWN
Platform: UNKNOWN
